README.md
setup.py
al_model_trainer.egg-info/PKG-INFO
al_model_trainer.egg-info/SOURCES.txt
al_model_trainer.egg-info/dependency_links.txt
al_model_trainer.egg-info/not-zip-safe
al_model_trainer.egg-info/requires.txt
al_model_trainer.egg-info/top_level.txt
bytegain/__init__.py
bytegain/custom/__init__.py
bytegain/custom/__version__.py
bytegain/custom/cust/__init__.py
bytegain/custom/cust/apartmentlist/__init__.py
bytegain/custom/cust/apartmentlist/al_clickstream_to_csv.py
bytegain/custom/cust/apartmentlist/al_finance.py
bytegain/custom/cust/apartmentlist/al_handler_from_features.py
bytegain/custom/cust/apartmentlist/al_multi_row_handler.py
bytegain/custom/cust/apartmentlist/al_xgb.py
bytegain/custom/cust/apartmentlist/clickstream_to_csv.py
bytegain/custom/cust/apartmentlist/clickstream_to_proto.py
bytegain/custom/cust/apartmentlist/common.py
bytegain/custom/cust/apartmentlist/compare_features.py
bytegain/custom/cust/apartmentlist/compare_with_events.py
bytegain/custom/cust/apartmentlist/create_tfrecords_from_dataset.py
bytegain/custom/cust/apartmentlist/data_science.py
bytegain/custom/cust/apartmentlist/feature_filter.py
bytegain/custom/cust/apartmentlist/generate_data_and_run_boost.py
bytegain/custom/cust/apartmentlist/instance_generator.py
bytegain/custom/cust/apartmentlist/interest_created.py
bytegain/custom/cust/apartmentlist/lstm_pipeline.py
bytegain/custom/cust/apartmentlist/matched.py
bytegain/custom/cust/apartmentlist/s3_to_gcp.py
bytegain/custom/cust/apartmentlist/s3_to_gcp_files.py
bytegain/custom/cust/apartmentlist/s3_to_proto.py
bytegain/custom/cust/apartmentlist/search_data.py
bytegain/custom/cust/apartmentlist/test_boost_classifiers.py
bytegain/custom/cust/apartmentlist/test_boosts.py
bytegain/custom/cust/apartmentlist/train_model.py
bytegain/custom/cust/apartmentlist/al_logs_feature_analysis/__init__.py
bytegain/custom/cust/apartmentlist/al_logs_feature_analysis/auto_analyze.py
bytegain/custom/cust/apartmentlist/al_logs_feature_analysis/compare_features.py
bytegain/custom/cust/apartmentlist/al_logs_feature_analysis/feature_analysis.py
bytegain/custom/cust/apartmentlist/lease_model/__init__.py
bytegain/custom/cust/apartmentlist/lease_model/instance_generator.py
