Metadata-Version: 1.0
Name: al-model-trainer
Version: 0.3.0
Summary: ByteGain Custom Model code
Home-page: https://github.com/apartmentlist/bytegain-training
Author: Tom Collier
Author-email: collier@apartmentlist.com
License: Commercial
Platform: UNKNOWN
